CHANGELOG.rst
LICENSE.txt
MANIFEST.in
README.rst
requirements.txt
setup.cfg
setup.py
versioneer.py
httpsig_pure_hmac/__init__.py
httpsig_pure_hmac/_version.py
httpsig_pure_hmac/requests_auth.py
httpsig_pure_hmac/sign.py
httpsig_pure_hmac/utils.py
httpsig_pure_hmac/verify.py
httpsig_pure_hmac.egg-info/PKG-INFO
httpsig_pure_hmac.egg-info/SOURCES.txt
httpsig_pure_hmac.egg-info/dependency_links.txt
httpsig_pure_hmac.egg-info/requires.txt
httpsig_pure_hmac.egg-info/top_level.txt
httpsig_pure_hmac.egg-info/zip-safe
httpsig_pure_hmac/tests/__init__.py
httpsig_pure_hmac/tests/test_signature.py
httpsig_pure_hmac/tests/test_utils.py
httpsig_pure_hmac/tests/test_verify.py