Metadata-Version: 1.1
Name: httpsig-pure-hmac
Version: 1.1.2
Summary: Fork of httpsig. HMAC only, no RSA, no PyCrypto, pure Python.
Home-page: https://github.com/alexanderlukanin13/httpsig-pure-hmac
Author: Alexander Lukanin
Author-email: alexander.lukanin.13@gmail.com
License: MIT
Keywords: http,authorization,api,web
Platform: UNKNOWN
Classifier: Development Status :: 5 - Production/Stable
Classifier: Environment :: Web Environment
Classifier: Intended Audience :: Developers
Classifier: License :: OSI Approved :: MIT License
Classifier: Operating System :: OS Independent
Classifier: Programming Language :: Python
Classifier: Programming Language :: Python :: 2.7
Classifier: Programming Language :: Python :: 3.3
Classifier: Programming Language :: Python :: 3.4
Classifier: Programming Language :: Python :: 3.4
Classifier: Programming Language :: Python :: 3.5
Classifier: Programming Language :: Python :: 3.6
Classifier: Topic :: Internet :: WWW/HTTP
Classifier: Topic :: Software Development :: Libraries :: Python Modules
